fluidfft_builder/__init__.py
fluidfft_builder/create_fake_mod_for_doc.py
fluidfft_builder/make_cy_files.py
fluidfft_builder/include_cy/base.pyx
fluidfft_builder/include_cy/base_mpi.pyx
fluidfft_builder/include_cy/cpu.pxd
fluidfft_builder/include_cy/util_pyfftw.pyx
fluidfft_builder/src_cpp/base_fft.cpp
fluidfft_builder/src_cpp/base_fft.h
fluidfft_builder/src_cpp/base_fft2d.cpp
fluidfft_builder/src_cpp/base_fft2d.h
fluidfft_builder/src_cpp/base_fft2dmpi.cpp
fluidfft_builder/src_cpp/base_fft2dmpi.h
fluidfft_builder/src_cpp/base_fft3d.cpp
fluidfft_builder/src_cpp/base_fft3d.h
fluidfft_builder/src_cpp/base_fft3dmpi.cpp
fluidfft_builder/src_cpp/base_fft3dmpi.h
fluidfft_builder/src_cpp/base_fftmpi.cpp
fluidfft_builder/src_cpp/base_fftmpi.h
fluidfft_builder/src_cpp/cpu.h
fluidfft_builder/src_cpp/cpu_builtin.h
fluidfft_builder/src_cpp/mainpage.h
fluidfft_builder/src_cpp/mpi-compat.h
fluidfft_builder/templates/__init__.py
fluidfft_builder/templates/template2d.pxd
fluidfft_builder/templates/template2d.pyx
fluidfft_builder/templates/template3d.pxd
fluidfft_builder/templates/template3d.pyx
fluidfft_builder-0.0.2.dist-info/entry_points.txt
fluidfft_builder-0.0.2.dist-info/LICENSE
fluidfft_builder-0.0.2.dist-info/WHEEL
fluidfft_builder-0.0.2.dist-info/METADATA
fluidfft_builder-0.0.2.dist-info/RECORD
