Metadata-Version: 2.1
Name: fluidfft-builder
Version: 0.0.2
Summary: Fluidfft plugin dependencies
Author-email: Pierre Augier <pierre.augier@univ-grenoble-alpes.fr>
Classifier: License :: OSI Approved :: MIT License
Project-URL: Home, https://foss.heptapod.net/fluiddyn/fluidfft
